{"upload_date": "20170329", "vcodec": "avc1.4d400b", "extractor": "youtube", "series": null, "chapters": null, "height": 144, "like_count": 3, "duration": 881, "fulltitle": "\u5173\u4e8e\u7f8e\u56fd\u5408\u6cd5\u6301\u67aa\u7684\u95ee\u9898", "id": "knh5CA9mmq4", "album": null, "view_count": 170, "playlist": "Uploads from Faye Hu", "start_time": null, "title": "\u5173\u4e8e\u7f8e\u56fd\u5408\u6cd5\u6301\u67aa\u7684\u95ee\u9898", "_filename": "20170329_NA_knh5CA9mmq4.mp4", "creator": null, "is_live": null, "playlist_index": 162, "dislike_count": 0, "playlist_id": "UUheuDxi3s2WAefGCbLHwqAw", "abr": 48, "tags": ["\u7f8e\u56fd\u67aa\u68b0\u95ee\u9898", "\u7f8e\u56fd\u5408\u6cd5\u6301\u67aa", "\u7f8e\u56fd\u6cd5\u5f8b", "\u7f8e\u56fd\u751f\u6d3b", "\u7f8e\u56fd\u95ee\u9898", "\u67aa\u652f\u95ee\u9898", "\u4f55\u8c13\u5408\u6cd5", "\u7f8e\u56fd\u67aa\u68b0\u6cd5\u89c4"], "uploader_url": "http://www.youtube.com/channel/UCheuDxi3s2WAefGCbLHwqAw", "subtitles": {}, "fps": 30, "stretched_ratio": null, "season_number": null, "annotations": null, "webpage_url_basename": "knh5CA9mmq4", "acodec": "mp4a.40.5", "display_id": "knh5CA9mmq4", "automatic_captions": {}, "description": "\u4f55\u8c13\u5408\u6cd5\u6301\u67aa\uff1f", "format": "160 - 256x144 (DASH video)+139 - audio only (DASH audio)", "track": null, "playlist_uploader": "Faye Hu", "average_rating": null, "uploader": "Faye Hu", "format_id": "160+139", "episode_number": null, "uploader_id": "UCheuDxi3s2WAefGCbLHwqAw", "categories": ["Comedy"], "playlist_title": "Uploads from Faye Hu", "thumbnails": [{"url": "https://i.ytimg.com/vi/knh5CA9mmq4/hqdefault.jpg", "id": "0"}], "license": null, "artist": null, "extractor_key": "Youtube", "release_date": null, "alt_title": null, "channel_id": null, "thumbnail": "https://i.ytimg.com/vi/knh5CA9mmq4/hqdefault.jpg", "vbr": null, "ext": "mp4", "release_year": null, "end_time": null, "webpage_url": "https://www.youtube.com/watch?v=knh5CA9mmq4", "formats": [{"asr": 22050, "tbr": 52.146, "protocol": "http_dash_segments", "format": "139 - audio only (DASH audio)", "format_note": "DASH audio", "height": null, "manifest_url": "https://manifest.googlevideo.com/api/manifest/dash/requiressl/yes/source/youtube/id/927879080f669aae/itag/0/ei/m9zRXKrTBcmFkwbt1KmIDQ/playback_host/r4---sn-a5mekned.googlevideo.com/mm/31%2C29/mn/sn-a5mekned%2Csn-a5msen7l/ms/au%2Crdu/mv/u/pl/21/hfr/all/as/fmp4_audio_clear%2Cwebm_audio_clear%2Cwebm2_audio_clear%2Cfmp4_sd_hd_clear%2Cwebm2_sd_hd_clear/mt/1557256637/fvip/4/ip/155.94.169.201/ipbits/0/expire/1557278971/sparams/ip%2Cipbits%2Cexpire%2Crequiressl%2Csource%2Cid%2Citag%2Cei%2Cplayback_host%2Cmm%2Cmn%2Cms%2Cmv%2Cpl%2Chfr%2Cas/signature/319BA1EDC6E89450A1E09D016A42A5F1C79312CF.2E001FDB1F390B70F17C7E28CA70DFE8E7CBB689/key/yt8", "format_id": "139", "container": "m4a_dash", "language": null, "http_headers": {"Accept-Charset": "ISO-8859-1,utf-8;q=0.7,*;q=0.7", "Accept-Language": "en-us,en;q=0.5", "Accept-Encoding": "gzip, deflate", "Accept": "text/html,application/xhtml+xml,application/xml;q=0.9,*/*;q=0.8", "User-Agent": "Mozilla/5.0 (X11; Linux x86_64; rv:59.0) Gecko/20100101 Firefox/59.0"}, "url": "https://manifest.googlevideo.com/api/manifest/dash/requiressl/yes/source/youtube/id/927879080f669aae/itag/0/ei/m9zRXKrTBcmFkwbt1KmIDQ/playback_host/r4---sn-a5mekned.googlevideo.com/mm/31%2C29/mn/sn-a5mekned%2Csn-a5msen7l/ms/au%2Crdu/mv/u/pl/21/hfr/all/as/fmp4_audio_clear%2Cwebm_audio_clear%2Cwebm2_audio_clear%2Cfmp4_sd_hd_clear%2Cwebm2_sd_hd_clear/mt/1557256637/fvip/4/ip/155.94.169.201/ipbits/0/expire/1557278971/sparams/ip%2Cipbits%2Cexpire%2Crequiressl%2Csource%2Cid%2Citag%2Cei%2Cplayback_host%2Cmm%2Cmn%2Cms%2Cmv%2Cpl%2Chfr%2Cas/signature/319BA1EDC6E89450A1E09D016A42A5F1C79312CF.2E001FDB1F390B70F17C7E28CA70DFE8E7CBB689/key/yt8", "vcodec": "none", "abr": 48, "width": null, "ext": "m4a", "fragment_base_url": "https://r4---sn-a5mekned.googlevideo.com/videoplayback/id/927879080f669aae/itag/139/source/youtube/requiressl/yes/ei/m9zRXKrTBcmFkwbt1KmIDQ/mm/31,29/mn/sn-a5mekned,sn-a5msen7l/ms/au,rdu/mv/u/pl/21/ratebypass/yes/mime/audio%2Fmp4/otfp/1/gir/yes/clen/5249762/lmt/1490807399215008/dur/880.918/mt/1557256637/fvip/4/disable_polymer/true/ip/155.94.169.201/ipbits/0/expire/1557278971/sparams/ip,ipbits,expire,id,itag,source,requiressl,ei,mm,mn,ms,mv,pl,ratebypass,mime,otfp,gir,clen,lmt,dur/signature/6D30B3B55B289E84293F263E54A29641C5D2C0C0.017093630D0323DEC07714A33CD854D0697194E3/key/dg_yt0/", "filesize": null, "fps": null, "fragments": [{"path": "range/0-593"}, {"duration": 5.016, "path": "range/2750-32695"}, {"duration": 5.015, "path": "range/32696-62569"}, {"duration": 4.969, "path": "range/62570-92133"}, {"duration": 5.016, "path": "range/92134-122081"}, {"duration": 5.015, "path": "range/122082-151978"}, {"duration": 4.969, "path": "range/151979-181555"}, {"duration": 5.016, "path": "range/181556-211396"}, {"duration": 5.015, "path": "range/211397-241238"}, {"duration": 4.969, "path": "range/241239-270812"}, {"duration": 5.016, "path": "range/270813-300748"}, {"duration": 5.015, "path": "range/300749-330581"}, {"duration": 4.969, "path": "range/330582-360331"}, {"duration": 5.016, "path": "range/360332-390071"}, {"duration": 5.015, "path": "range/390072-420018"}, {"duration": 4.969, "path": "range/420019-449641"}, {"duration": 5.016, "path": "range/449642-479422"}, {"duration": 5.015, "path": "range/479423-509286"}, {"duration": 4.97, "path": "range/509287-538939"}, {"duration": 5.015, "path": "range/538940-568776"}, {"duration": 5.016, "path": "range/568777-598657"}, {"duration": 4.969, "path": "range/598658-628302"}, {"duration": 5.015, "path": "range/628303-658126"}, {"duration": 5.016, "path": "range/658127-688015"}, {"duration": 4.969, "path": "range/688016-717600"}, {"duration": 5.015, "path": "range/717601-747472"}, {"duration": 5.016, "path": "range/747473-777304"}, {"duration": 4.969, "path": "range/777305-806929"}, {"duration": 5.015, "path": "range/806930-836805"}, {"duration": 5.016, "path": "range/836806-866712"}, {"duration": 4.969, "path": "range/866713-896297"}, {"duration": 5.015, "path": "range/896298-926251"}, {"duration": 5.016, "path": "range/926252-956095"}, {"duration": 4.969, "path": "range/956096-985604"}, {"duration": 5.015, "path": "range/985605-1015485"}, {"duration": 5.016, "path": "range/1015486-1045375"}, {"duration": 4.969, "path": "range/1045376-1074941"}, {"duration": 5.016, "path": "range/1074942-1104849"}, {"duration": 5.015, "path": "range/1104850-1134762"}, {"duration": 4.969, "path": "range/1134763-1164365"}, {"duration": 5.016, "path": "range/1164366-1194139"}, {"duration": 5.015, "path": "range/1194140-1224131"}, {"duration": 4.969, "path": "range/1224132-1253697"}, {"duration": 5.016, "path": "range/1253698-1283477"}, {"duration": 5.015, "path": "range/1283478-1313358"}, {"duration": 4.969, "path": "range/1313359-1343003"}, {"duration": 5.016, "path": "range/1343004-1372857"}, {"duration": 5.015, "path": "range/1372858-1402722"}, {"duration": 4.969, "path": "range/1402723-1432316"}, {"duration": 5.016, "path": "range/1432317-1462285"}, {"duration": 5.015, "path": "range/1462286-1492073"}, {"duration": 4.97, "path": "range/1492074-1521682"}, {"duration": 5.015, "path": "range/1521683-1551611"}, {"duration": 5.016, "path": "range/1551612-1581483"}, {"duration": 4.969, "path": "range/1581484-1610997"}, {"duration": 5.015, "path": "range/1610998-1640968"}, {"duration": 5.016, "path": "range/1640969-1670816"}, {"duration": 4.969, "path": "range/1670817-1700348"}, {"duration": 5.015, "path": "range/1700349-1730261"}, {"duration": 5.016, "path": "range/1730262-1760121"}, {"duration": 4.969, "path": "range/1760122-1789685"}, {"duration": 5.015, "path": "range/1789686-1819595"}, {"duration": 5.016, "path": "range/1819596-1849540"}, {"duration": 4.969, "path": "range/1849541-1879048"}, {"duration": 5.015, "path": "range/1879049-1908948"}, {"duration": 5.016, "path": "range/1908949-1938843"}, {"duration": 4.969, "path": "range/1938844-1968385"}, {"duration": 5.015, "path": "range/1968386-1998315"}, {"duration": 5.016, "path": "range/1998316-2028093"}, {"duration": 4.969, "path": "range/2028094-2057714"}, {"duration": 5.016, "path": "range/2057715-2087677"}, {"duration": 5.015, "path": "range/2087678-2117498"}, {"duration": 4.969, "path": "range/2117499-2147085"}, {"duration": 5.016, "path": "range/2147086-2176986"}, {"duration": 5.015, "path": "range/2176987-2206881"}, {"duration": 4.969, "path": "range/2206882-2236476"}, {"duration": 5.016, "path": "range/2236477-2266360"}, {"duration": 5.015, "path": "range/2266361-2296164"}, {"duration": 4.969, "path": "range/2296165-2325745"}, {"duration": 5.016, "path": "range/2325746-2355643"}, {"duration": 5.015, "path": "range/2355644-2385588"}, {"duration": 4.969, "path": "range/2385589-2415123"}, {"duration": 5.016, "path": "range/2415124-2445081"}, {"duration": 5.015, "path": "range/2445082-2474873"}, {"duration": 4.97, "path": "range/2474874-2504519"}, {"duration": 5.015, "path": "range/2504520-2534383"}, {"duration": 5.016, "path": "range/2534384-2564164"}, {"duration": 4.969, "path": "range/2564165-2593956"}, {"duration": 5.015, "path": "range/2593957-2623747"}, {"duration": 5.016, "path": "range/2623748-2653545"}, {"duration": 4.969, "path": "range/2653546-2683165"}, {"duration": 5.015, "path": "range/2683166-2713024"}, {"duration": 5.016, "path": "range/2713025-2742872"}, {"duration": 4.969, "path": "range/2742873-2772570"}, {"duration": 5.015, "path": "range/2772571-2802434"}, {"duration": 5.016, "path": "range/2802435-2832248"}, {"duration": 4.969, "path": "range/2832249-2861809"}, {"duration": 5.015, "path": "range/2861810-2891724"}, {"duration": 5.016, "path": "range/2891725-2921561"}, {"duration": 4.969, "path": "range/2921562-2951135"}, {"duration": 5.015, "path": "range/2951136-2981073"}, {"duration": 5.016, "path": "range/2981074-3010970"}, {"duration": 4.969, "path": "range/3010971-3040469"}, {"duration": 5.016, "path": "range/3040470-3070410"}, {"duration": 5.015, "path": "range/3070411-3100268"}, {"duration": 4.969, "path": "range/3100269-3129822"}, {"duration": 5.016, "path": "range/3129823-3159733"}, {"duration": 5.015, "path": "range/3159734-3189610"}, {"duration": 4.969, "path": "range/3189611-3219203"}, {"duration": 5.016, "path": "range/3219204-3249138"}, {"duration": 5.015, "path": "range/3249139-3279002"}, {"duration": 4.969, "path": "range/3279003-3308538"}, {"duration": 5.016, "path": "range/3308539-3338454"}, {"duration": 5.015, "path": "range/3338455-3368293"}, {"duration": 4.969, "path": "range/3368294-3397901"}, {"duration": 5.016, "path": "range/3397902-3427794"}, {"duration": 5.015, "path": "range/3427795-3457660"}, {"duration": 4.97, "path": "range/3457661-3487326"}, {"duration": 5.015, "path": "range/3487327-3517095"}, {"duration": 5.016, "path": "range/3517096-3547048"}, {"duration": 4.969, "path": "range/3547049-3576671"}, {"duration": 5.015, "path": "range/3576672-3606479"}, {"duration": 5.016, "path": "range/3606480-3636350"}, {"duration": 4.969, "path": "range/3636351-3665949"}, {"duration": 5.015, "path": "range/3665950-3695784"}, {"duration": 5.016, "path": "range/3695785-3725649"}, {"duration": 4.969, "path": "range/3725650-3755302"}, {"duration": 5.015, "path": "range/3755303-3785126"}, {"duration": 5.016, "path": "range/3785127-3815032"}, {"duration": 4.969, "path": "range/3815033-3844609"}, {"duration": 5.015, "path": "range/3844610-3874640"}, {"duration": 5.016, "path": "range/3874641-3904375"}, {"duration": 4.969, "path": "range/3904376-3934013"}, {"duration": 5.015, "path": "range/3934014-3963842"}, {"duration": 5.016, "path": "range/3963843-3993794"}, {"duration": 4.969, "path": "range/3993795-4023294"}, {"duration": 5.016, "path": "range/4023295-4053278"}, {"duration": 5.015, "path": "range/4053279-4083053"}, {"duration": 4.969, "path": "range/4083054-4112630"}, {"duration": 5.016, "path": "range/4112631-4142561"}, {"duration": 5.015, "path": "range/4142562-4172449"}, {"duration": 4.969, "path": "range/4172450-4202002"}, {"duration": 5.016, "path": "range/4202003-4231832"}, {"duration": 5.015, "path": "range/4231833-4261729"}, {"duration": 4.969, "path": "range/4261730-4291356"}, {"duration": 5.016, "path": "range/4291357-4321156"}, {"duration": 5.015, "path": "range/4321157-4351062"}, {"duration": 4.969, "path": "range/4351063-4380670"}, {"duration": 5.016, "path": "range/4380671-4410556"}, {"duration": 5.015, "path": "range/4410557-4440472"}, {"duration": 4.969, "path": "range/4440473-4470061"}, {"duration": 5.016, "path": "range/4470062-4499867"}, {"duration": 5.016, "path": "range/4499868-4529791"}, {"duration": 4.969, "path": "range/4529792-4559353"}, {"duration": 5.015, "path": "range/4559354-4589266"}, {"duration": 5.016, "path": "range/4589267-4619215"}, {"duration": 4.969, "path": "range/4619216-4648745"}, {"duration": 5.015, "path": "range/4648746-4678584"}, {"duration": 5.016, "path": "range/4678585-4708504"}, {"duration": 4.969, "path": "range/4708505-4738103"}, {"duration": 5.015, "path": "range/4738104-4767891"}, {"duration": 5.016, "path": "range/4767892-4797805"}, {"duration": 4.969, "path": "range/4797806-4827488"}, {"duration": 5.015, "path": "range/4827489-4857241"}, {"duration": 5.016, "path": "range/4857242-4887159"}, {"duration": 4.969, "path": "range/4887160-4916818"}, {"duration": 5.015, "path": "range/4916819-4946583"}, {"duration": 5.016, "path": "range/4946584-4976479"}, {"duration": 4.969, "path": "range/4976480-5006060"}, {"duration": 5.016, "path": "range/5006061-5035940"}, {"duration": 5.015, "path": "range/5035941-5065884"}, {"duration": 4.969, "path": "range/5065885-5095404"}, {"duration": 5.016, "path": "range/5095405-5125304"}, {"duration": 5.015, "path": "range/5125305-5155179"}, {"duration": 4.969, "path": "range/5155180-5184745"}, {"duration": 5.016, "path": "range/5184746-5214647"}, {"duration": 5.015, "path": "range/5214648-5244545"}, {"duration": 0.882, "path": "range/5244546-5249761"}], "acodec": "mp4a.40.5"}, {"asr": 44100, "tbr": 99.738, "protocol": "http_dash_segments", "format": "140 - audio only (DASH audio)", "format_note": "DASH audio", "height": null, "manifest_url": "https://manifest.googlevideo.com/api/manifest/dash/requiressl/yes/source/youtube/id/927879080f669aae/itag/0/ei/m9zRXKrTBcmFkwbt1KmIDQ/playback_host/r4---sn-a5mekned.googlevideo.com/mm/31%2C29/mn/sn-a5mekned%2Csn-a5msen7l/ms/au%2Crdu/mv/u/pl/21/hfr/all/as/fmp4_audio_clear%2Cwebm_audio_clear%2Cwebm2_audio_clear%2Cfmp4_sd_hd_clear%2Cwebm2_sd_hd_clear/mt/1557256637/fvip/4/ip/155.94.169.201/ipbits/0/expire/1557278971/sparams/ip%2Cipbits%2Cexpire%2Crequiressl%2Csource%2Cid%2Citag%2Cei%2Cplayback_host%2Cmm%2Cmn%2Cms%2Cmv%2Cpl%2Chfr%2Cas/signature/319BA1EDC6E89450A1E09D016A42A5F1C79312CF.2E001FDB1F390B70F17C7E28CA70DFE8E7CBB689/key/yt8", "format_id": "140", "container": "m4a_dash", "language": null, "http_headers": {"Accept-Charset": "ISO-8859-1,utf-8;q=0.7,*;q=0.7", "Accept-Language": "en-us,en;q=0.5", "Accept-Encoding": "gzip, deflate", "Accept": "text/html,application/xhtml+xml,application/xml;q=0.9,*/*;q=0.8", "User-Agent": "Mozilla/5.0 (X11; Linux x86_64; rv:59.0) Gecko/20100101 Firefox/59.0"}, "url": "https://manifest.googlevideo.com/api/manifest/dash/requiressl/yes/source/youtube/id/927879080f669aae/itag/0/ei/m9zRXKrTBcmFkwbt1KmIDQ/playback_host/r4---sn-a5mekned.googlevideo.com/mm/31%2C29/mn/sn-a5mekned%2Csn-a5msen7l/ms/au%2Crdu/mv/u/pl/21/hfr/all/as/fmp4_audio_clear%2Cwebm_audio_clear%2Cwebm2_audio_clear%2Cfmp4_sd_hd_clear%2Cwebm2_sd_hd_clear/mt/1557256637/fvip/4/ip/155.94.169.201/ipbits/0/expire/1557278971/sparams/ip%2Cipbits%2Cexpire%2Crequiressl%2Csource%2Cid%2Citag%2Cei%2Cplayback_host%2Cmm%2Cmn%2Cms%2Cmv%2Cpl%2Chfr%2Cas/signature/319BA1EDC6E89450A1E09D016A42A5F1C79312CF.2E001FDB1F390B70F17C7E28CA70DFE8E7CBB689/key/yt8", "vcodec": "none", "abr": 128, "width": null, "ext": "m4a", "fragment_base_url": "https://r4---sn-a5mekned.googlevideo.com/videoplayback/id/927879080f669aae/itag/140/source/youtube/requiressl/yes/ei/m9zRXKrTBcmFkwbt1KmIDQ/mm/31,29/mn/sn-a5mekned,sn-a5msen7l/ms/au,rdu/mv/u/pl/21/ratebypass/yes/mime/audio%2Fmp4/otfp/1/gir/yes/clen/10477538/lmt/1490807399214926/dur/880.848/mt/1557256637/fvip/4/disable_polymer/true/ip/155.94.169.201/ipbits/0/expire/1557278971/sparams/ip,ipbits,expire,id,itag,source,requiressl,ei,mm,mn,ms,mv,pl,ratebypass,mime,otfp,gir,clen,lmt,dur/signature/73696206F431B20B6917668FA7F0FFA7D2410B75.6FB2C12FDA531E9CAC476EAC903284E82A860864/key/dg_yt0/", "filesize": null, "fps": null, "fragments": [{"path": "range/0-591"}, {"duration": 5.016, "path": "range/2748-62535"}, {"duration": 5.015, "path": "range/62536-121802"}, {"duration": 4.969, "path": "range/121803-181209"}, {"duration": 5.016, "path": "range/181210-240883"}, {"duration": 5.015, "path": "range/240884-300242"}, {"duration": 4.969, "path": "range/300243-359651"}, {"duration": 5.016, "path": "range/359652-419187"}, {"duration": 5.015, "path": "range/419188-478599"}, {"duration": 4.969, "path": "range/478600-537956"}, {"duration": 5.016, "path": "range/537957-597624"}, {"duration": 5.015, "path": "range/597625-657014"}, {"duration": 4.969, "path": "range/657015-716371"}, {"duration": 5.016, "path": "range/716372-775978"}, {"duration": 5.015, "path": "range/775979-835380"}, {"duration": 4.969, "path": "range/835381-894739"}, {"duration": 5.016, "path": "range/894740-954370"}, {"duration": 5.015, "path": "range/954371-1013700"}, {"duration": 4.97, "path": "range/1013701-1073139"}, {"duration": 5.015, "path": "range/1073140-1132759"}, {"duration": 5.016, "path": "range/1132760-1192173"}, {"duration": 4.969, "path": "range/1192174-1251522"}, {"duration": 5.015, "path": "range/1251523-1311108"}, {"duration": 5.016, "path": "range/1311109-1370479"}, {"duration": 4.969, "path": "range/1370480-1429857"}, {"duration": 5.015, "path": "range/1429858-1489475"}, {"duration": 5.016, "path": "range/1489476-1548872"}, {"duration": 4.969, "path": "range/1548873-1608297"}, {"duration": 5.015, "path": "range/1608298-1667852"}, {"duration": 5.016, "path": "range/1667853-1727225"}, {"duration": 4.969, "path": "range/1727226-1786607"}, {"duration": 5.015, "path": "range/1786608-1846342"}, {"duration": 5.016, "path": "range/1846343-1905589"}, {"duration": 4.969, "path": "range/1905590-1965024"}, {"duration": 5.015, "path": "range/1965025-2024611"}, {"duration": 5.016, "path": "range/2024612-2083986"}, {"duration": 4.969, "path": "range/2083987-2143301"}, {"duration": 5.016, "path": "range/2143302-2202998"}, {"duration": 5.015, "path": "range/2202999-2262341"}, {"duration": 4.969, "path": "range/2262342-2321799"}, {"duration": 5.016, "path": "range/2321800-2381333"}, {"duration": 5.015, "path": "range/2381334-2440797"}, {"duration": 4.969, "path": "range/2440798-2500165"}, {"duration": 5.016, "path": "range/2500166-2559731"}, {"duration": 5.015, "path": "range/2559732-2619060"}, {"duration": 4.969, "path": "range/2619061-2678462"}, {"duration": 5.016, "path": "range/2678463-2738120"}, {"duration": 5.015, "path": "range/2738121-2797462"}, {"duration": 4.969, "path": "range/2797463-2856844"}, {"duration": 5.016, "path": "range/2856845-2916479"}, {"duration": 5.015, "path": "range/2916480-2975828"}, {"duration": 4.97, "path": "range/2975829-3035202"}, {"duration": 5.015, "path": "range/3035203-3094927"}, {"duration": 5.016, "path": "range/3094928-3154266"}, {"duration": 4.969, "path": "range/3154267-3213606"}, {"duration": 5.015, "path": "range/3213607-3273236"}, {"duration": 5.016, "path": "range/3273237-3332626"}, {"duration": 4.969, "path": "range/3332627-3391983"}, {"duration": 5.015, "path": "range/3391984-3451600"}, {"duration": 5.016, "path": "range/3451601-3510960"}, {"duration": 4.969, "path": "range/3510961-3570309"}, {"duration": 5.015, "path": "range/3570310-3629979"}, {"duration": 5.016, "path": "range/3629980-3689397"}, {"duration": 4.969, "path": "range/3689398-3748707"}, {"duration": 5.015, "path": "range/3748708-3808408"}, {"duration": 5.016, "path": "range/3808409-3867727"}, {"duration": 4.969, "path": "range/3867728-3927069"}, {"duration": 5.015, "path": "range/3927070-3986778"}, {"duration": 5.016, "path": "range/3986779-4046097"}, {"duration": 4.969, "path": "range/4046098-4105460"}, {"duration": 5.016, "path": "range/4105461-4165152"}, {"duration": 5.015, "path": "range/4165153-4224463"}, {"duration": 4.969, "path": "range/4224464-4283912"}, {"duration": 5.016, "path": "range/4283913-4343581"}, {"duration": 5.015, "path": "range/4343582-4402807"}, {"duration": 4.969, "path": "range/4402808-4462282"}, {"duration": 5.016, "path": "range/4462283-4521941"}, {"duration": 5.015, "path": "range/4521942-4581249"}, {"duration": 4.969, "path": "range/4581250-4640578"}, {"duration": 5.016, "path": "range/4640579-4700209"}, {"duration": 5.015, "path": "range/4700210-4759633"}, {"duration": 4.969, "path": "range/4759634-4819041"}, {"duration": 5.016, "path": "range/4819042-4878659"}, {"duration": 5.015, "path": "range/4878660-4937954"}, {"duration": 4.97, "path": "range/4937955-4997404"}, {"duration": 5.015, "path": "range/4997405-5057017"}, {"duration": 5.016, "path": "range/5057018-5116385"}, {"duration": 4.969, "path": "range/5116386-5175709"}, {"duration": 5.015, "path": "range/5175710-5235414"}, {"duration": 5.016, "path": "range/5235415-5294701"}, {"duration": 4.969, "path": "range/5294702-5354112"}, {"duration": 5.015, "path": "range/5354113-5413737"}, {"duration": 5.016, "path": "range/5413738-5473084"}, {"duration": 4.969, "path": "range/5473085-5532484"}, {"duration": 5.015, "path": "range/5532485-5592205"}, {"duration": 5.016, "path": "range/5592206-5651519"}, {"duration": 4.969, "path": "range/5651520-5710859"}, {"duration": 5.015, "path": "range/5710860-5770504"}, {"duration": 5.016, "path": "range/5770505-5829850"}, {"duration": 4.969, "path": "range/5829851-5889219"}, {"duration": 5.015, "path": "range/5889220-5948841"}, {"duration": 5.016, "path": "range/5948842-6008239"}, {"duration": 4.969, "path": "range/6008240-6067587"}, {"duration": 5.016, "path": "range/6067588-6127237"}, {"duration": 5.015, "path": "range/6127238-6186645"}, {"duration": 4.969, "path": "range/6186646-6245921"}, {"duration": 5.016, "path": "range/6245922-6305604"}, {"duration": 5.015, "path": "range/6305605-6364962"}, {"duration": 4.969, "path": "range/6364963-6424342"}, {"duration": 5.016, "path": "range/6424343-6483961"}, {"duration": 5.015, "path": "range/6483962-6543363"}, {"duration": 4.969, "path": "range/6543364-6602714"}, {"duration": 5.016, "path": "range/6602715-6662408"}, {"duration": 5.015, "path": "range/6662409-6721710"}, {"duration": 4.969, "path": "range/6721711-6781074"}, {"duration": 5.016, "path": "range/6781075-6840755"}, {"duration": 5.015, "path": "range/6840756-6900073"}, {"duration": 4.97, "path": "range/6900074-6959494"}, {"duration": 5.015, "path": "range/6959495-7019097"}, {"duration": 5.016, "path": "range/7019098-7078474"}, {"duration": 4.969, "path": "range/7078475-7137850"}, {"duration": 5.015, "path": "range/7137851-7197492"}, {"duration": 5.016, "path": "range/7197493-7256903"}, {"duration": 4.969, "path": "range/7256904-7316263"}, {"duration": 5.015, "path": "range/7316264-7375837"}, {"duration": 5.016, "path": "range/7375838-7435238"}, {"duration": 4.969, "path": "range/7435239-7494642"}, {"duration": 5.015, "path": "range/7494643-7554258"}, {"duration": 5.016, "path": "range/7554259-7613602"}, {"duration": 4.969, "path": "range/7613603-7673006"}, {"duration": 5.015, "path": "range/7673007-7732668"}, {"duration": 5.016, "path": "range/7732669-7791975"}, {"duration": 4.969, "path": "range/7791976-7851387"}, {"duration": 5.015, "path": "range/7851388-7910991"}, {"duration": 5.016, "path": "range/7910992-7970346"}, {"duration": 4.969, "path": "range/7970347-8029742"}, {"duration": 5.016, "path": "range/8029743-8089466"}, {"duration": 5.015, "path": "range/8089467-8148729"}, {"duration": 4.969, "path": "range/8148730-8208165"}, {"duration": 5.016, "path": "range/8208166-8267804"}, {"duration": 5.015, "path": "range/8267805-8327150"}, {"duration": 4.969, "path": "range/8327151-8386439"}, {"duration": 5.016, "path": "range/8386440-8446107"}, {"duration": 5.015, "path": "range/8446108-8505451"}, {"duration": 4.969, "path": "range/8505452-8564857"}, {"duration": 5.016, "path": "range/8564858-8624542"}, {"duration": 5.015, "path": "range/8624543-8683864"}, {"duration": 4.969, "path": "range/8683865-8743208"}, {"duration": 5.016, "path": "range/8743209-8802946"}, {"duration": 5.015, "path": "range/8802947-8862296"}, {"duration": 4.969, "path": "range/8862297-8921607"}, {"duration": 5.016, "path": "range/8921608-8981240"}, {"duration": 5.016, "path": "range/8981241-9040575"}, {"duration": 4.969, "path": "range/9040576-9099935"}, {"duration": 5.015, "path": "range/9099936-9159643"}, {"duration": 5.016, "path": "range/9159644-9219003"}, {"duration": 4.969, "path": "range/9219004-9278348"}, {"duration": 5.015, "path": "range/9278349-9337961"}, {"duration": 5.016, "path": "range/9337962-9397477"}, {"duration": 4.969, "path": "range/9397478-9456723"}, {"duration": 5.015, "path": "range/9456724-9516310"}, {"duration": 5.016, "path": "range/9516311-9575790"}, {"duration": 4.969, "path": "range/9575791-9635207"}, {"duration": 5.015, "path": "range/9635208-9694797"}, {"duration": 5.016, "path": "range/9694798-9754200"}, {"duration": 4.969, "path": "range/9754201-9813573"}, {"duration": 5.015, "path": "range/9813574-9873067"}, {"duration": 5.016, "path": "range/9873068-9932494"}, {"duration": 4.969, "path": "range/9932495-9991847"}, {"duration": 5.016, "path": "range/9991848-10051469"}, {"duration": 5.015, "path": "range/10051470-10110848"}, {"duration": 4.969, "path": "range/10110849-10170183"}, {"duration": 5.016, "path": "range/10170184-10229847"}, {"duration": 5.015, "path": "range/10229848-10289200"}, {"duration": 4.969, "path": "range/10289201-10348545"}, {"duration": 5.016, "path": "range/10348546-10408261"}, {"duration": 5.015, "path": "range/10408262-10467627"}, {"duration": 0.882, "path": "range/10467628-10477537"}], "acodec": "mp4a.40.2"}, {"asr": null, "tbr": 108.0, "protocol": "http_dash_segments", "format": "160 - 256x144 (DASH video)", "format_note": "DASH video", "height": 144, "manifest_url": "https://manifest.googlevideo.com/api/manifest/dash/requiressl/yes/source/youtube/id/927879080f669aae/itag/0/ei/m9zRXKrTBcmFkwbt1KmIDQ/playback_host/r4---sn-a5mekned.googlevideo.com/mm/31%2C29/mn/sn-a5mekned%2Csn-a5msen7l/ms/au%2Crdu/mv/u/pl/21/hfr/all/as/fmp4_audio_clear%2Cwebm_audio_clear%2Cwebm2_audio_clear%2Cfmp4_sd_hd_clear%2Cwebm2_sd_hd_clear/mt/1557256637/fvip/4/ip/155.94.169.201/ipbits/0/expire/1557278971/sparams/ip%2Cipbits%2Cexpire%2Crequiressl%2Csource%2Cid%2Citag%2Cei%2Cplayback_host%2Cmm%2Cmn%2Cms%2Cmv%2Cpl%2Chfr%2Cas/signature/319BA1EDC6E89450A1E09D016A42A5F1C79312CF.2E001FDB1F390B70F17C7E28CA70DFE8E7CBB689/key/yt8", "format_id": "160", "container": "mp4_dash", "language": null, "http_headers": {"Accept-Charset": "ISO-8859-1,utf-8;q=0.7,*;q=0.7", "Accept-Language": "en-us,en;q=0.5", "Accept-Encoding": "gzip, deflate", "Accept": "text/html,application/xhtml+xml,application/xml;q=0.9,*/*;q=0.8", "User-Agent": "Mozilla/5.0 (X11; Linux x86_64; rv:59.0) Gecko/20100101 Firefox/59.0"}, "url": "https://manifest.googlevideo.com/api/manifest/dash/requiressl/yes/source/youtube/id/927879080f669aae/itag/0/ei/m9zRXKrTBcmFkwbt1KmIDQ/playback_host/r4---sn-a5mekned.googlevideo.com/mm/31%2C29/mn/sn-a5mekned%2Csn-a5msen7l/ms/au%2Crdu/mv/u/pl/21/hfr/all/as/fmp4_audio_clear%2Cwebm_audio_clear%2Cwebm2_audio_clear%2Cfmp4_sd_hd_clear%2Cwebm2_sd_hd_clear/mt/1557256637/fvip/4/ip/155.94.169.201/ipbits/0/expire/1557278971/sparams/ip%2Cipbits%2Cexpire%2Crequiressl%2Csource%2Cid%2Citag%2Cei%2Cplayback_host%2Cmm%2Cmn%2Cms%2Cmv%2Cpl%2Chfr%2Cas/signature/319BA1EDC6E89450A1E09D016A42A5F1C79312CF.2E001FDB1F390B70F17C7E28CA70DFE8E7CBB689/key/yt8", "vcodec": "avc1.4d400b", "width": 256, "ext": "mp4", "fragment_base_url": "https://r4---sn-a5mekned.googlevideo.com/videoplayback/id/927879080f669aae/itag/160/source/yt_otf/requiressl/yes/ei/m9zRXKrTBcmFkwbt1KmIDQ/mm/31,29/mn/sn-a5mekned,sn-a5msen7l/ms/au,rdu/mv/u/pl/21/ratebypass/yes/mime/video%2Fmp4/otfp/1/otf/1/lmt/1490807380084627/mt/1557256637/fvip/4/disable_polymer/true/ip/155.94.169.201/ipbits/0/expire/1557278971/sparams/ip,ipbits,expire,id,itag,source,requiressl,ei,mm,mn,ms,mv,pl,ratebypass,mime,otfp,otf,lmt/signature/463FE2A54697C8BF9F5320BA7F9CAF81AB6BC356.704216A6860000C6AE15726BBC7B27611F1DF8B7/key/dg_yt0/", "filesize": null, "fps": 30, "fragments": [{"path": "sq/0"}, {"duration": 5.333, "path": "sq/1/dur/5.333"}, {"duration": 5.334, "path": "sq/2/dur/5.334"}, {"duration": 5.333, "path": "sq/3/dur/5.333"}, {"duration": 5.333, "path": "sq/4/dur/5.333"}, {"duration": 5.334, "path": "sq/5/dur/5.334"}, {"duration": 5.333, "path": "sq/6/dur/5.333"}, {"duration": 5.333, "path": "sq/7/dur/5.333"}, {"duration": 5.334, "path": "sq/8/dur/5.334"}, {"duration": 5.333, "path": "sq/9/dur/5.333"}, {"duration": 5.333, "path": "sq/10/dur/5.333"}, {"duration": 5.334, "path": "sq/11/dur/5.334"}, {"duration": 5.333, "path": "sq/12/dur/5.333"}, {"duration": 5.333, "path": "sq/13/dur/5.333"}, {"duration": 5.334, "path": "sq/14/dur/5.334"}, {"duration": 5.333, "path": "sq/15/dur/5.333"}, {"duration": 5.333, "path": "sq/16/dur/5.333"}, {"duration": 5.334, "path": "sq/17/dur/5.334"}, {"duration": 5.333, "path": "sq/18/dur/5.333"}, {"duration": 5.333, "path": "sq/19/dur/5.333"}, {"duration": 5.334, "path": "sq/20/dur/5.334"}, {"duration": 5.333, "path": "sq/21/dur/5.333"}, {"duration": 5.333, "path": "sq/22/dur/5.333"}, {"duration": 5.334, "path": "sq/23/dur/5.334"}, {"duration": 5.333, "path": "sq/24/dur/5.333"}, {"duration": 5.333, "path": "sq/25/dur/5.333"}, {"duration": 5.334, "path": "sq/26/dur/5.334"}, {"duration": 5.333, "path": "sq/27/dur/5.333"}, {"duration": 5.333, "path": "sq/28/dur/5.333"}, {"duration": 5.334, "path": "sq/29/dur/5.334"}, {"duration": 5.333, "path": "sq/30/dur/5.333"}, {"duration": 5.333, "path": "sq/31/dur/5.333"}, {"duration": 5.334, "path": "sq/32/dur/5.334"}, {"duration": 5.333, "path": "sq/33/dur/5.333"}, {"duration": 5.333, "path": "sq/34/dur/5.333"}, {"duration": 5.334, "path": "sq/35/dur/5.334"}, {"duration": 5.333, "path": "sq/36/dur/5.333"}, {"duration": 5.333, "path": "sq/37/dur/5.333"}, {"duration": 5.334, "path": "sq/38/dur/5.334"}, {"duration": 5.333, "path": "sq/39/dur/5.333"}, {"duration": 5.333, "path": "sq/40/dur/5.333"}, {"duration": 5.334, "path": "sq/41/dur/5.334"}, {"duration": 5.333, "path": "sq/42/dur/5.333"}, {"duration": 5.333, "path": "sq/43/dur/5.333"}, {"duration": 5.334, "path": "sq/44/dur/5.334"}, {"duration": 5.333, "path": "sq/45/dur/5.333"}, {"duration": 5.333, "path": "sq/46/dur/5.333"}, {"duration": 5.334, "path": "sq/47/dur/5.334"}, {"duration": 5.333, "path": "sq/48/dur/5.333"}, {"duration": 5.333, "path": "sq/49/dur/5.333"}, {"duration": 5.334, "path": "sq/50/dur/5.334"}, {"duration": 5.333, "path": "sq/51/dur/5.333"}, {"duration": 5.333, "path": "sq/52/dur/5.333"}, {"duration": 5.334, "path": "sq/53/dur/5.334"}, {"duration": 5.333, "path": "sq/54/dur/5.333"}, {"duration": 5.333, "path": "sq/55/dur/5.333"}, {"duration": 5.334, "path": "sq/56/dur/5.334"}, {"duration": 5.333, "path": "sq/57/dur/5.333"}, {"duration": 5.333, "path": "sq/58/dur/5.333"}, {"duration": 5.334, "path": "sq/59/dur/5.334"}, {"duration": 5.333, "path": "sq/60/dur/5.333"}, {"duration": 5.333, "path": "sq/61/dur/5.333"}, {"duration": 5.334, "path": "sq/62/dur/5.334"}, {"duration": 5.333, "path": "sq/63/dur/5.333"}, {"duration": 5.333, "path": "sq/64/dur/5.333"}, {"duration": 5.334, "path": "sq/65/dur/5.334"}, {"duration": 5.333, "path": "sq/66/dur/5.333"}, {"duration": 5.333, "path": "sq/67/dur/5.333"}, {"duration": 5.334, "path": "sq/68/dur/5.334"}, {"duration": 5.333, "path": "sq/69/dur/5.333"}, {"duration": 5.333, "path": "sq/70/dur/5.333"}, {"duration": 5.334, "path": "sq/71/dur/5.334"}, {"duration": 5.333, "path": "sq/72/dur/5.333"}, {"duration": 5.333, "path": "sq/73/dur/5.333"}, {"duration": 5.334, "path": "sq/74/dur/5.334"}, {"duration": 5.333, "path": "sq/75/dur/5.333"}, {"duration": 5.333, "path": "sq/76/dur/5.333"}, {"duration": 5.334, "path": "sq/77/dur/5.334"}, {"duration": 5.333, "path": "sq/78/dur/5.333"}, {"duration": 5.333, "path": "sq/79/dur/5.333"}, {"duration": 5.334, "path": "sq/80/dur/5.334"}, {"duration": 5.333, "path": "sq/81/dur/5.333"}, {"duration": 5.333, "path": "sq/82/dur/5.333"}, {"duration": 5.334, "path": "sq/83/dur/5.334"}, {"duration": 5.333, "path": "sq/84/dur/5.333"}, {"duration": 5.333, "path": "sq/85/dur/5.333"}, {"duration": 5.334, "path": "sq/86/dur/5.334"}, {"duration": 5.333, "path": "sq/87/dur/5.333"}, {"duration": 5.333, "path": "sq/88/dur/5.333"}, {"duration": 5.334, "path": "sq/89/dur/5.334"}, {"duration": 5.333, "path": "sq/90/dur/5.333"}, {"duration": 5.333, "path": "sq/91/dur/5.333"}, {"duration": 5.334, "path": "sq/92/dur/5.334"}, {"duration": 5.333, "path": "sq/93/dur/5.333"}, {"duration": 5.333, "path": "sq/94/dur/5.333"}, {"duration": 5.334, "path": "sq/95/dur/5.334"}, {"duration": 5.333, "path": "sq/96/dur/5.333"}, {"duration": 5.333, "path": "sq/97/dur/5.333"}, {"duration": 5.334, "path": "sq/98/dur/5.334"}, {"duration": 5.333, "path": "sq/99/dur/5.333"}, {"duration": 5.333, "path": "sq/100/dur/5.333"}, {"duration": 5.334, "path": "sq/101/dur/5.334"}, {"duration": 5.333, "path": "sq/102/dur/5.333"}, {"duration": 5.333, "path": "sq/103/dur/5.333"}, {"duration": 5.334, "path": "sq/104/dur/5.334"}, {"duration": 5.333, "path": "sq/105/dur/5.333"}, {"duration": 5.333, "path": "sq/106/dur/5.333"}, {"duration": 5.334, "path": "sq/107/dur/5.334"}, {"duration": 5.333, "path": "sq/108/dur/5.333"}, {"duration": 5.333, "path": "sq/109/dur/5.333"}, {"duration": 5.334, "path": "sq/110/dur/5.334"}, {"duration": 5.333, "path": "sq/111/dur/5.333"}, {"duration": 5.333, "path": "sq/112/dur/5.333"}, {"duration": 5.334, "path": "sq/113/dur/5.334"}, {"duration": 5.333, "path": "sq/114/dur/5.333"}, {"duration": 5.333, "path": "sq/115/dur/5.333"}, {"duration": 5.334, "path": "sq/116/dur/5.334"}, {"duration": 5.333, "path": "sq/117/dur/5.333"}, {"duration": 5.333, "path": "sq/118/dur/5.333"}, {"duration": 5.334, "path": "sq/119/dur/5.334"}, {"duration": 5.333, "path": "sq/120/dur/5.333"}, {"duration": 5.333, "path": "sq/121/dur/5.333"}, {"duration": 5.334, "path": "sq/122/dur/5.334"}, {"duration": 5.333, "path": "sq/123/dur/5.333"}, {"duration": 5.333, "path": "sq/124/dur/5.333"}, {"duration": 5.334, "path": "sq/125/dur/5.334"}, {"duration": 5.333, "path": "sq/126/dur/5.333"}, {"duration": 5.333, "path": "sq/127/dur/5.333"}, {"duration": 5.334, "path": "sq/128/dur/5.334"}, {"duration": 5.333, "path": "sq/129/dur/5.333"}, {"duration": 5.333, "path": "sq/130/dur/5.333"}, {"duration": 5.334, "path": "sq/131/dur/5.334"}, {"duration": 5.333, "path": "sq/132/dur/5.333"}, {"duration": 5.333, "path": "sq/133/dur/5.333"}, {"duration": 5.334, "path": "sq/134/dur/5.334"}, {"duration": 5.333, "path": "sq/135/dur/5.333"}, {"duration": 5.333, "path": "sq/136/dur/5.333"}, {"duration": 5.334, "path": "sq/137/dur/5.334"}, {"duration": 5.333, "path": "sq/138/dur/5.333"}, {"duration": 5.333, "path": "sq/139/dur/5.333"}, {"duration": 5.334, "path": "sq/140/dur/5.334"}, {"duration": 5.333, "path": "sq/141/dur/5.333"}, {"duration": 5.333, "path": "sq/142/dur/5.333"}, {"duration": 5.334, "path": "sq/143/dur/5.334"}, {"duration": 5.333, "path": "sq/144/dur/5.333"}, {"duration": 5.333, "path": "sq/145/dur/5.333"}, {"duration": 5.334, "path": "sq/146/dur/5.334"}, {"duration": 5.333, "path": "sq/147/dur/5.333"}, {"duration": 5.333, "path": "sq/148/dur/5.333"}, {"duration": 5.334, "path": "sq/149/dur/5.334"}, {"duration": 5.333, "path": "sq/150/dur/5.333"}, {"duration": 5.333, "path": "sq/151/dur/5.333"}, {"duration": 5.334, "path": "sq/152/dur/5.334"}, {"duration": 5.333, "path": "sq/153/dur/5.333"}, {"duration": 5.333, "path": "sq/154/dur/5.333"}, {"duration": 5.334, "path": "sq/155/dur/5.334"}, {"duration": 5.333, "path": "sq/156/dur/5.333"}, {"duration": 5.333, "path": "sq/157/dur/5.333"}, {"duration": 5.334, "path": "sq/158/dur/5.334"}, {"duration": 5.333, "path": "sq/159/dur/5.333"}, {"duration": 5.333, "path": "sq/160/dur/5.333"}, {"duration": 5.334, "path": "sq/161/dur/5.334"}, {"duration": 5.333, "path": "sq/162/dur/5.333"}, {"duration": 5.333, "path": "sq/163/dur/5.333"}, {"duration": 5.334, "path": "sq/164/dur/5.334"}, {"duration": 6.133, "path": "sq/165/dur/6.133"}], "acodec": "none"}, {"asr": null, "tbr": 251.222, "protocol": "http_dash_segments", "format": "133 - 426x240 (DASH video)", "format_note": "DASH video", "height": 240, "manifest_url": "https://manifest.googlevideo.com/api/manifest/dash/requiressl/yes/source/youtube/id/927879080f669aae/itag/0/ei/m9zRXKrTBcmFkwbt1KmIDQ/playback_host/r4---sn-a5mekned.googlevideo.com/mm/31%2C29/mn/sn-a5mekned%2Csn-a5msen7l/ms/au%2Crdu/mv/u/pl/21/hfr/all/as/fmp4_audio_clear%2Cwebm_audio_clear%2Cwebm2_audio_clear%2Cfmp4_sd_hd_clear%2Cwebm2_sd_hd_clear/mt/1557256637/fvip/4/ip/155.94.169.201/ipbits/0/expire/1557278971/sparams/ip%2Cipbits%2Cexpire%2Crequiressl%2Csource%2Cid%2Citag%2Cei%2Cplayback_host%2Cmm%2Cmn%2Cms%2Cmv%2Cpl%2Chfr%2Cas/signature/319BA1EDC6E89450A1E09D016A42A5F1C79312CF.2E001FDB1F390B70F17C7E28CA70DFE8E7CBB689/key/yt8", "format_id": "133", "container": "mp4_dash", "language": null, "http_headers": {"Accept-Charset": "ISO-8859-1,utf-8;q=0.7,*;q=0.7", "Accept-Language": "en-us,en;q=0.5", "Accept-Encoding": "gzip, deflate", "Accept": "text/html,application/xhtml+xml,application/xml;q=0.9,*/*;q=0.8", "User-Agent": "Mozilla/5.0 (X11; Linux x86_64; rv:59.0) Gecko/20100101 Firefox/59.0"}, "url": "https://manifest.googlevideo.com/api/manifest/dash/requiressl/yes/source/youtube/id/927879080f669aae/itag/0/ei/m9zRXKrTBcmFkwbt1KmIDQ/playback_host/r4---sn-a5mekned.googlevideo.com/mm/31%2C29/mn/sn-a5mekned%2Csn-a5msen7l/ms/au%2Crdu/mv/u/pl/21/hfr/all/as/fmp4_audio_clear%2Cwebm_audio_clear%2Cwebm2_audio_clear%2Cfmp4_sd_hd_clear%2Cwebm2_sd_hd_clear/mt/1557256637/fvip/4/ip/155.94.169.201/ipbits/0/expire/1557278971/sparams/ip%2Cipbits%2Cexpire%2Crequiressl%2Csource%2Cid%2Citag%2Cei%2Cplayback_host%2Cmm%2Cmn%2Cms%2Cmv%2Cpl%2Chfr%2Cas/signature/319BA1EDC6E89450A1E09D016A42A5F1C79312CF.2E001FDB1F390B70F17C7E28CA70DFE8E7CBB689/key/yt8", "vcodec": "avc1.4d4015", "width": 426, "ext": "mp4", "fragment_base_url": "https://r4---sn-a5mekned.googlevideo.com/videoplayback/id/927879080f669aae/itag/133/source/youtube/requiressl/yes/ei/m9zRXKrTBcmFkwbt1KmIDQ/mm/31,29/mn/sn-a5mekned,sn-a5msen7l/ms/au,rdu/mv/u/pl/21/ratebypass/yes/mime/video%2Fmp4/otfp/1/gir/yes/clen/26920729/lmt/1490807380084627/dur/880.799/mt/1557256637/fvip/4/disable_polymer/true/ip/155.94.169.201/ipbits/0/expire/1557278971/sparams/ip,ipbits,expire,id,itag,source,requiressl,ei,mm,mn,ms,mv,pl,ratebypass,mime,otfp,gir,clen,lmt,dur/signature/49B6F4EA93DA409D079104F1C736015405FB2B91.6447C3F285D28B353869F54FB9A28FE4E610DDEB/key/dg_yt0/", "filesize": null, "fps": 30, "fragments": [{"path": "range/0-713"}, {"duration": 5.333, "path": "range/2726-167470"}, {"duration": 5.334, "path": "range/167471-330034"}, {"duration": 5.333, "path": "range/330035-494278"}, {"duration": 5.333, "path": "range/494279-658241"}, {"duration": 5.334, "path": "range/658242-823119"}, {"duration": 5.333, "path": "range/823120-985412"}, {"duration": 5.333, "path": "range/985413-1149149"}, {"duration": 5.334, "path": "range/1149150-1312136"}, {"duration": 5.333, "path": "range/1312137-1474949"}, {"duration": 5.333, "path": "range/1474950-1639016"}, {"duration": 5.334, "path": "range/1639017-1801885"}, {"duration": 5.333, "path": "range/1801886-1964595"}, {"duration": 5.333, "path": "range/1964596-2127555"}, {"duration": 5.334, "path": "range/2127556-2291793"}, {"duration": 5.333, "path": "range/2291794-2453783"}, {"duration": 5.333, "path": "range/2453784-2616368"}, {"duration": 5.334, "path": "range/2616369-2779368"}, {"duration": 5.333, "path": "range/2779369-2942105"}, {"duration": 5.333, "path": "range/2942106-3105985"}, {"duration": 5.334, "path": "range/3105986-3268659"}, {"duration": 5.333, "path": "range/3268660-3431628"}, {"duration": 5.333, "path": "range/3431629-3594144"}, {"duration": 5.334, "path": "range/3594145-3759313"}, {"duration": 5.333, "path": "range/3759314-3922671"}, {"duration": 5.333, "path": "range/3922672-4085739"}, {"duration": 5.334, "path": "range/4085740-4247874"}, {"duration": 5.333, "path": "range/4247875-4410167"}, {"duration": 5.333, "path": "range/4410168-4574178"}, {"duration": 5.334, "path": "range/4574179-4736114"}, {"duration": 5.333, "path": "range/4736115-4899003"}, {"duration": 5.333, "path": "range/4899004-5062227"}, {"duration": 5.334, "path": "range/5062228-5225579"}, {"duration": 5.333, "path": "range/5225580-5388596"}, {"duration": 5.333, "path": "range/5388597-5551053"}, {"duration": 5.334, "path": "range/5551054-5714200"}, {"duration": 5.333, "path": "range/5714201-5876069"}, {"duration": 5.333, "path": "range/5876070-6040163"}, {"duration": 5.334, "path": "range/6040164-6204695"}, {"duration": 5.333, "path": "range/6204696-6367981"}, {"duration": 5.333, "path": "range/6367982-6531164"}, {"duration": 5.334, "path": "range/6531165-6693834"}, {"duration": 5.333, "path": "range/6693835-6857575"}, {"duration": 5.333, "path": "range/6857576-7019702"}, {"duration": 5.334, "path": "range/7019703-7182140"}, {"duration": 5.333, "path": "range/7182141-7345640"}, {"duration": 5.333, "path": "range/7345641-7508478"}, {"duration": 5.334, "path": "range/7508479-7670604"}, {"duration": 5.333, "path": "range/7670605-7834270"}, {"duration": 5.333, "path": "range/7834271-7996871"}, {"duration": 5.334, "path": "range/7996872-8160714"}, {"duration": 5.333, "path": "range/8160715-8323183"}, {"duration": 5.333, "path": "range/8323184-8486393"}, {"duration": 5.334, "path": "range/8486394-8649900"}, {"duration": 5.333, "path": "range/8649901-8813081"}, {"duration": 5.333, "path": "range/8813082-8977443"}, {"duration": 5.334, "path": "range/8977444-9140157"}, {"duration": 5.333, "path": "range/9140158-9303213"}, {"duration": 5.333, "path": "range/9303214-9466127"}, {"duration": 5.334, "path": "range/9466128-9628726"}, {"duration": 5.333, "path": "range/9628727-9790811"}, {"duration": 5.333, "path": "range/9790812-9952607"}, {"duration": 5.334, "path": "range/9952608-10114102"}, {"duration": 5.333, "path": "range/10114103-10277283"}, {"duration": 5.333, "path": "range/10277284-10439474"}, {"duration": 5.334, "path": "range/10439475-10602473"}, {"duration": 5.333, "path": "range/10602474-10765457"}, {"duration": 5.333, "path": "range/10765458-10927574"}, {"duration": 5.334, "path": "range/10927575-11091334"}, {"duration": 5.333, "path": "range/11091335-11254466"}, {"duration": 5.333, "path": "range/11254467-11416539"}, {"duration": 5.334, "path": "range/11416540-11579431"}, {"duration": 5.333, "path": "range/11579432-11742679"}, {"duration": 5.333, "path": "range/11742680-11908247"}, {"duration": 5.334, "path": "range/11908248-12071848"}, {"duration": 5.333, "path": "range/12071849-12236165"}, {"duration": 5.333, "path": "range/12236166-12398102"}, {"duration": 5.334, "path": "range/12398103-12559859"}, {"duration": 5.333, "path": "range/12559860-12722959"}, {"duration": 5.333, "path": "range/12722960-12885966"}, {"duration": 5.334, "path": "range/12885967-13049193"}, {"duration": 5.333, "path": "range/13049194-13211529"}, {"duration": 5.333, "path": "range/13211530-13374308"}, {"duration": 5.334, "path": "range/13374309-13536950"}, {"duration": 5.333, "path": "range/13536951-13700561"}, {"duration": 5.333, "path": "range/13700562-13864031"}, {"duration": 5.334, "path": "range/13864032-14025771"}, {"duration": 5.333, "path": "range/14025772-14187993"}, {"duration": 5.333, "path": "range/14187994-14350104"}, {"duration": 5.334, "path": "range/14350105-14512287"}, {"duration": 5.333, "path": "range/14512288-14676078"}, {"duration": 5.333, "path": "range/14676079-14839430"}, {"duration": 5.334, "path": "range/14839431-15000564"}, {"duration": 5.333, "path": "range/15000565-15162772"}, {"duration": 5.333, "path": "range/15162773-15327207"}, {"duration": 5.334, "path": "range/15327208-15490605"}, {"duration": 5.333, "path": "range/15490606-15654372"}, {"duration": 5.333, "path": "range/15654373-15816811"}, {"duration": 5.334, "path": "range/15816812-15980305"}, {"duration": 5.333, "path": "range/15980306-16143272"}, {"duration": 5.333, "path": "range/16143273-16306414"}, {"duration": 5.334, "path": "range/16306415-16469889"}, {"duration": 5.333, "path": "range/16469890-16634888"}, {"duration": 5.333, "path": "range/16634889-16796732"}, {"duration": 5.334, "path": "range/16796733-16957942"}, {"duration": 5.333, "path": "range/16957943-17119696"}, {"duration": 5.333, "path": "range/17119697-17281696"}, {"duration": 5.334, "path": "range/17281697-17443888"}, {"duration": 5.333, "path": "range/17443889-17606720"}, {"duration": 5.333, "path": "range/17606721-17769728"}, {"duration": 5.334, "path": "range/17769729-17932621"}, {"duration": 5.333, "path": "range/17932622-18094916"}, {"duration": 5.333, "path": "range/18094917-18257527"}, {"duration": 5.334, "path": "range/18257528-18419322"}, {"duration": 5.333, "path": "range/18419323-18582130"}, {"duration": 5.333, "path": "range/18582131-18744528"}, {"duration": 5.334, "path": "range/18744529-18908224"}, {"duration": 5.333, "path": "range/18908225-19071473"}, {"duration": 5.333, "path": "range/19071474-19234698"}, {"duration": 5.334, "path": "range/19234699-19396095"}, {"duration": 5.333, "path": "range/19396096-19559122"}, {"duration": 5.333, "path": "range/19559123-19721968"}, {"duration": 5.334, "path": "range/19721969-19884532"}, {"duration": 5.333, "path": "range/19884533-20047959"}, {"duration": 5.333, "path": "range/20047960-20211258"}, {"duration": 5.334, "path": "range/20211259-20374665"}, {"duration": 5.333, "path": "range/20374666-20538893"}, {"duration": 5.333, "path": "range/20538894-20702275"}, {"duration": 5.334, "path": "range/20702276-20864406"}, {"duration": 5.333, "path": "range/20864407-21024941"}, {"duration": 5.333, "path": "range/21024942-21189076"}, {"duration": 5.334, "path": "range/21189077-21353848"}, {"duration": 5.333, "path": "range/21353849-21515408"}, {"duration": 5.333, "path": "range/21515409-21678205"}, {"duration": 5.334, "path": "range/21678206-21843402"}, {"duration": 5.333, "path": "range/21843403-22005102"}, {"duration": 5.333, "path": "range/22005103-22167099"}, {"duration": 5.334, "path": "range/22167100-22328812"}, {"duration": 5.333, "path": "range/22328813-22492544"}, {"duration": 5.333, "path": "range/22492545-22655373"}, {"duration": 5.334, "path": "range/22655374-22819028"}, {"duration": 5.333, "path": "range/22819029-22982284"}, {"duration": 5.333, "path": "range/22982285-23146038"}, {"duration": 5.334, "path": "range/23146039-23311626"}, {"duration": 5.333, "path": "range/23311627-23475577"}, {"duration": 5.333, "path": "range/23475578-23638249"}, {"duration": 5.334, "path": "range/23638250-23801036"}, {"duration": 5.333, "path": "range/23801037-23963651"}, {"duration": 5.333, "path": "range/23963652-24127297"}, {"duration": 5.334, "path": "range/24127298-24290690"}, {"duration": 5.333, "path": "range/24290691-24452879"}, {"duration": 5.333, "path": "range/24452880-24615571"}, {"duration": 5.334, "path": "range/24615572-24778992"}, {"duration": 5.333, "path": "range/24778993-24941281"}, {"duration": 5.333, "path": "range/24941282-25105157"}, {"duration": 5.334, "path": "range/25105158-25268651"}, {"duration": 5.333, "path": "range/25268652-25432152"}, {"duration": 5.333, "path": "range/25432153-25594747"}, {"duration": 5.334, "path": "range/25594748-25757387"}, {"duration": 5.333, "path": "range/25757388-25921356"}, {"duration": 5.333, "path": "range/25921357-26084126"}, {"duration": 5.334, "path": "range/26084127-26246254"}, {"duration": 5.333, "path": "range/26246255-26408738"}, {"duration": 5.333, "path": "range/26408739-26570946"}, {"duration": 5.334, "path": "range/26570947-26734436"}, {"duration": 6.133, "path": "range/26734437-26920728"}], "acodec": "none"}, {"http_headers": {"Accept-Charset": "ISO-8859-1,utf-8;q=0.7,*;q=0.7", "Accept-Language": "en-us,en;q=0.5", "Accept-Encoding": "gzip, deflate", "Accept": "text/html,application/xhtml+xml,application/xml;q=0.9,*/*;q=0.8", "User-Agent": "Mozilla/5.0 (X11; Linux x86_64; rv:59.0) Gecko/20100101 Firefox/59.0"}, "protocol": "https", "format": "18 - 568x320 (medium)", "url": "https://r4---sn-a5mekned.googlevideo.com/videoplayback?id=o-AEwnyXS3lSc2JDPsRfxujvA3EyXJKH_C6H6j8mQtxscQ&itag=18&source=youtube&requiressl=yes&mm=31%2C29&mn=sn-a5mekned%2Csn-a5msen7l&ms=au%2Crdu&mv=u&pl=21&ei=m9zRXKrTBcmFkwbt1KmIDQ&mime=video%2Fmp4&gir=yes&clen=44163192&ratebypass=yes&dur=880.848&lmt=1490807409515593&mt=1557256637&fvip=4&c=WEB&ip=155.94.169.201&ipbits=0&expire=1557278971&sparams=ip%2Cipbits%2Cexpire%2Cid%2Citag%2Csource%2Crequiressl%2Cmm%2Cmn%2Cms%2Cmv%2Cpl%2Cei%2Cmime%2Cgir%2Cclen%2Cratebypass%2Cdur%2Clmt&signature=B5A6861C47140C21A5001AACA43DDE7E0374B8DC.76FF50270551D9280407462A5428E631FB2C77CC&key=yt8", "quality": 1, "vcodec": "avc1.42001E", "format_note": "medium", "ext": "mp4", "player_url": "/yts/jsbin/player_ias-vflisCO7O/en_US/base.js", "width": 568, "abr": 96, "filesize": 44163192, "format_id": "18", "height": 320, "resolution": "568x320", "acodec": "mp4a.40.2"}, {"http_headers": {"Accept-Charset": "ISO-8859-1,utf-8;q=0.7,*;q=0.7", "Accept-Language": "en-us,en;q=0.5", "Accept-Encoding": "gzip, deflate", "Accept": "text/html,application/xhtml+xml,application/xml;q=0.9,*/*;q=0.8", "User-Agent": "Mozilla/5.0 (X11; Linux x86_64; rv:59.0) Gecko/20100101 Firefox/59.0"}, "protocol": "https", "format": "43 - 640x360 (medium)", "url": "https://r4---sn-a5mekned.googlevideo.com/videoplayback?id=o-AEwnyXS3lSc2JDPsRfxujvA3EyXJKH_C6H6j8mQtxscQ&itag=43&source=youtube&requiressl=yes&mm=31%2C29&mn=sn-a5mekned%2Csn-a5msen7l&ms=au%2Crdu&mv=u&pl=21&ei=m9zRXKrTBcmFkwbt1KmIDQ&mime=video%2Fwebm&gir=yes&clen=67846567&ratebypass=yes&dur=0.000&lmt=1490811445244283&mt=1557256637&fvip=4&c=WEB&ip=155.94.169.201&ipbits=0&expire=1557278971&sparams=ip%2Cipbits%2Cexpire%2Cid%2Citag%2Csource%2Crequiressl%2Cmm%2Cmn%2Cms%2Cmv%2Cpl%2Cei%2Cmime%2Cgir%2Cclen%2Cratebypass%2Cdur%2Clmt&signature=04D1FB4D0C40C842BE42BD376A7412BB90175760.3FFC8E92D7F51499D581294EA01C8A92D2843D14&key=yt8", "quality": 1, "vcodec": "vp8.0", "format_note": "medium", "ext": "webm", "player_url": "/yts/jsbin/player_ias-vflisCO7O/en_US/base.js", "width": 640, "abr": 128, "filesize": 67846567, "format_id": "43", "height": 360, "resolution": "640x360", "acodec": "vorbis"}], "playlist_uploader_id": "UCheuDxi3s2WAefGCbLHwqAw", "channel_url": null, "resolution": null, "width": 256, "n_entries": 227, "age_limit": 0}